tbh_secure_agents/__init__.py
tbh_secure_agents/agent.py
tbh_secure_agents/crew.py
tbh_secure_agents/exceptions.py
tbh_secure_agents/expert.py
tbh_secure_agents/logging_config.py
tbh_secure_agents/memory.py
tbh_secure_agents/operation.py
tbh_secure_agents/run_expert_test.py
tbh_secure_agents/security_profiles.py
tbh_secure_agents/squad.py
tbh_secure_agents/task.py
tbh_secure_agents/terminal_ui.py
tbh_secure_agents/test_session_memory_scale.py
tbh_secure_agents/security/__init__.py
tbh_secure_agents/security/agent_sentinel.py
tbh_secure_agents/security/data_guardian.py
tbh_secure_agents/security/prompt_defender.py
tbh_secure_agents/security/reliability_monitor.py
tbh_secure_agents/security_validation/__init__.py
tbh_secure_agents/security_validation/adaptive_security.py
tbh_secure_agents/security_validation/integration.py
tbh_secure_agents/security_validation/production_config.py
tbh_secure_agents/security_validation/production_integration.py
tbh_secure_agents/security_validation/recommendation_generator.py
tbh_secure_agents/security_validation/report_generator.py
tbh_secure_agents/security_validation/security_validator.py
tbh_secure_agents/security_validation/models/enhanced_dataset.py
tbh_secure_agents/security_validation/models/enhanced_training_data.py
tbh_secure_agents/security_validation/models/generate_security_dataset.py
tbh_secure_agents/security_validation/models/optimized_security_model.pkl
tbh_secure_agents/security_validation/models/train_optimized_model.py
tbh_secure_agents/security_validation/models/train_pipeline_model.py
tbh_secure_agents/security_validation/models/train_security_model.py
tbh_secure_agents/security_validation/models/data/security_model.pkl
tbh_secure_agents/security_validation/models/data/security_pipeline.pkl
tbh_secure_agents/security_validation/models/data/vectorizer.pkl
tbh_secure_agents/security_validation/models/data/enhanced/security_pipeline.pkl
tbh_secure_agents/security_validation/recommendation/__init__.py
tbh_secure_agents-0.5.4.dist-info/licenses/LICENSE
tbh_secure_agents-0.5.4.dist-info/METADATA
tbh_secure_agents-0.5.4.dist-info/WHEEL
tbh_secure_agents-0.5.4.dist-info/top_level.txt
tbh_secure_agents-0.5.4.dist-info/RECORD
