Metadata-Version: 2.4
Name: tbh-secure-agents
Version: 0.5.4
Summary: Secure Agents Framework with hybrid security validation
Author-email: TBH Team <dev@tbh.ai>
License: Apache-2.0
Project-URL: Homepage, https://github.com/saishshinde15/tbh.ai_SecureAgents-Developer_Edition-Alpha
Classifier: Development Status :: 4 - Beta
Classifier: Intended Audience :: Developers
Classifier: License :: OSI Approved :: Apache Software License
Classifier: Programming Language :: Python :: 3
Classifier: Programming Language :: Python :: 3.8
Classifier: Programming Language :: Python :: 3.9
Classifier: Programming Language :: Python :: 3.10
Classifier: Programming Language :: Python :: 3.11
Classifier: Programming Language :: Python :: 3.12
License-File: LICENSE
Dynamic: license-file
